[
    {
        "icao24": "a3539d",
        "callsign": "SKW3746 ",
        "origin_country": "United States",
        "time_position": 1750656427,
        "last_contact": 1750656427,
        "longitude": -117.1326,
        "latitude": 32.8435,
        "baro_altitude": 2156.46,
        "on_ground": false,
        "velocity": 134.11,
        "true_track": 138.42,
        "vertical_rate": -4.23,
        "sensors": null,
        "geo_altitude": 2202.18,
        "squawk": null,
        "spi": false,
        "position_source": 0,
        "category": 0
    },
    {
        "icao24": "a0f566",
        "callsign": "AAL1011 ",
        "origin_country": "United States",
        "time_position": 1750656427,
        "last_contact": 1750656427,
        "longitude": -115.7993,
        "latitude": 32.7932,
        "baro_altitude": 6408.42,
        "on_ground": false,
        "velocity": 204,
        "true_track": 258.8,
        "vertical_rate": -10.73,
        "sensors": null,
        "geo_altitude": 6720.84,
        "squawk": "0512",
        "spi": false,
        "position_source": 0,
        "category": 0
    },
    {
        "icao24": "aaaa4a",
        "callsign": "SWA4920 ",
        "origin_country": "United States",
        "time_position": 1750656426,
        "last_contact": 1750656426,
        "longitude": -117.0086,
        "latitude": 32.6897,
        "baro_altitude": 975.36,
        "on_ground": false,
        "velocity": 108.43,
        "true_track": 283.44,
        "vertical_rate": -6.18,
        "sensors": null,
        "geo_altitude": 975.36,
        "squawk": "3755",
        "spi": false,
        "position_source": 0,
        "category": 0
    },
    {
        "icao24": "a123e0",
        "callsign": "UAL1827 ",
        "origin_country": "United States",
        "time_position": 1750656426,
        "last_contact": 1750656426,
        "longitude": -117.2314,
        "latitude": 32.7482,
        "baro_altitude": 441.96,
        "on_ground": false,
        "velocity": 100.77,
        "true_track": 302.07,
        "vertical_rate": 4.88,
        "sensors": null,
        "geo_altitude": 411.48,
        "squawk": null,
        "spi": false,
        "position_source": 0,
        "category": 0
    },
    {
        "icao24": "a12227",
        "callsign": "N172RW  ",
        "origin_country": "United States",
        "time_position": 1750656373,
        "last_contact": 1750656373,
        "longitude": -117.1317,
        "latitude": 32.813,
        "baro_altitude": 152.4,
        "on_ground": false,
        "velocity": 33.17,
        "true_track": 293.78,
        "vertical_rate": -1.95,
        "sensors": null,
        "geo_altitude": 137.16,
        "squawk": null,
        "spi": false,
        "position_source": 0,
        "category": 0
    },
    {
        "icao24": "ace7aa",
        "callsign": "SWA4383 ",
        "origin_country": "United States",
        "time_position": 1750656366,
        "last_contact": 1750656366,
        "longitude": -117.1827,
        "latitude": 32.7308,
        "baro_altitude": null,
        "on_ground": true,
        "velocity": 6.94,
        "true_track": 106.88,
        "vertical_rate": null,
        "sensors": null,
        "geo_altitude": null,
        "squawk": null,
        "spi": false,
        "position_source": 0,
        "category": 0
    },
    {
        "icao24": "ac1a72",
        "callsign": "SWA486  ",
        "origin_country": "United States",
        "time_position": 1750656318,
        "last_contact": 1750656318,
        "longitude": -117.1818,
        "latitude": 32.7306,
        "baro_altitude": null,
        "on_ground": true,
        "velocity": 5.4,
        "true_track": 106.88,
        "vertical_rate": null,
        "sensors": null,
        "geo_altitude": null,
        "squawk": null,
        "spi": false,
        "position_source": 0,
        "category": 0
    },
    {
        "icao24": "ac0b7f",
        "callsign": "UAL1584 ",
        "origin_country": "United States",
        "time_position": 1750656426,
        "last_contact": 1750656427,
        "longitude": -117.016,
        "latitude": 32.7671,
        "baro_altitude": 1676.4,
        "on_ground": false,
        "velocity": 121.27,
        "true_track": 106.51,
        "vertical_rate": -3.9,
        "sensors": null,
        "geo_altitude": 1699.26,
        "squawk": "6312",
        "spi": false,
        "position_source": 0,
        "category": 0
    },
    {
        "icao24": "ac17b0",
        "callsign": "SWA3466 ",
        "origin_country": "United States",
        "time_position": 1750656427,
        "last_contact": 1750656427,
        "longitude": -115.988,
        "latitude": 32.7746,
        "baro_altitude": 5722.62,
        "on_ground": false,
        "velocity": 201.39,
        "true_track": 265.02,
        "vertical_rate": -11.38,
        "sensors": null,
        "geo_altitude": 5996.94,
        "squawk": "1324",
        "spi": false,
        "position_source": 0,
        "category": 0
    },
    {
        "icao24": "a25e79",
        "callsign": "CXK204  ",
        "origin_country": "United States",
        "time_position": 1750656427,
        "last_contact": 1750656427,
        "longitude": -117.2666,
        "latitude": 33.1305,
        "baro_altitude": 144.78,
        "on_ground": false,
        "velocity": 35.02,
        "true_track": 259.85,
        "vertical_rate": -3.58,
        "sensors": null,
        "geo_altitude": 114.3,
        "squawk": null,
        "spi": false,
        "position_source": 0,
        "category": 0
    },
    {
        "icao24": "ac2a8e",
        "callsign": "N883SD  ",
        "origin_country": "United States",
        "time_position": 1750656426,
        "last_contact": 1750656427,
        "longitude": -117.1881,
        "latitude": 32.7856,
        "baro_altitude": 746.76,
        "on_ground": false,
        "velocity": 34.56,
        "true_track": 274.27,
        "vertical_rate": 6.18,
        "sensors": null,
        "geo_altitude": 723.9,
        "squawk": null,
        "spi": false,
        "position_source": 0,
        "category": 0
    },
    {
        "icao24": "ad4afb",
        "callsign": "ASA1020 ",
        "origin_country": "United States",
        "time_position": 1750656326,
        "last_contact": 1750656326,
        "longitude": -117.1828,
        "latitude": 32.7309,
        "baro_altitude": null,
        "on_ground": true,
        "velocity": 6.69,
        "true_track": 106.88,
        "vertical_rate": null,
        "sensors": null,
        "geo_altitude": null,
        "squawk": null,
        "spi": false,
        "position_source": 0,
        "category": 0
    },
    {
        "icao24": "ac2b80",
        "callsign": "SWA909  ",
        "origin_country": "United States",
        "time_position": 1750656230,
        "last_contact": 1750656230,
        "longitude": -117.2008,
        "latitude": 32.7352,
        "baro_altitude": null,
        "on_ground": true,
        "velocity": 3.09,
        "true_track": 106.88,
        "vertical_rate": null,
        "sensors": null,
        "geo_altitude": null,
        "squawk": null,
        "spi": false,
        "position_source": 0,
        "category": 0
    }
]