[
    {
        "icao24": "a0f566",
        "callsign": "AAL1011 ",
        "origin_country": "United States",
        "time_position": 1750657395,
        "last_contact": 1750657398,
        "longitude": -117.1868,
        "latitude": 32.7329,
        "baro_altitude": -7.62,
        "on_ground": false,
        "velocity": 72.29,
        "true_track": 286.11,
        "vertical_rate": -0.33,
        "sensors": null,
        "geo_altitude": -30.48,
        "squawk": "0512",
        "spi": false,
        "position_source": 0,
        "category": 0
    },
    {
        "icao24": "a62c1a",
        "callsign": "SWA3245 ",
        "origin_country": "United States",
        "time_position": 1750657687,
        "last_contact": 1750657687,
        "longitude": -117.0138,
        "latitude": 32.6908,
        "baro_altitude": 1013.46,
        "on_ground": false,
        "velocity": 104.51,
        "true_track": 286.29,
        "vertical_rate": -6.5,
        "sensors": null,
        "geo_altitude": 1013.46,
        "squawk": null,
        "spi": false,
        "position_source": 0,
        "category": 0
    },
    {
        "icao24": "abef54",
        "callsign": "SWA3898 ",
        "origin_country": "United States",
        "time_position": 1750657610,
        "last_contact": 1750657610,
        "longitude": -117.1948,
        "latitude": 32.7337,
        "baro_altitude": null,
        "on_ground": true,
        "velocity": 4.63,
        "true_track": 120.94,
        "vertical_rate": null,
        "sensors": null,
        "geo_altitude": null,
        "squawk": null,
        "spi": false,
        "position_source": 0,
        "category": 0
    },
    {
        "icao24": "a506d5",
        "callsign": "ASA1005 ",
        "origin_country": "United States",
        "time_position": 1750657682,
        "last_contact": 1750657682,
        "longitude": -117.1838,
        "latitude": 32.7311,
        "baro_altitude": null,
        "on_ground": true,
        "velocity": 6.94,
        "true_track": 106.88,
        "vertical_rate": null,
        "sensors": null,
        "geo_altitude": null,
        "squawk": null,
        "spi": false,
        "position_source": 0,
        "category": 0
    },
    {
        "icao24": "ad0f29",
        "callsign": "SWA2426 ",
        "origin_country": "United States",
        "time_position": 1750657663,
        "last_contact": 1750657663,
        "longitude": -117.1828,
        "latitude": 32.7309,
        "baro_altitude": null,
        "on_ground": true,
        "velocity": 5.14,
        "true_track": 106.88,
        "vertical_rate": null,
        "sensors": null,
        "geo_altitude": null,
        "squawk": null,
        "spi": false,
        "position_source": 0,
        "category": 1
    },
    {
        "icao24": "ace7aa",
        "callsign": "SWA4383 ",
        "origin_country": "United States",
        "time_position": 1750657678,
        "last_contact": 1750657679,
        "longitude": -117.1882,
        "latitude": 32.7332,
        "baro_altitude": 7.62,
        "on_ground": false,
        "velocity": 73.92,
        "true_track": 286.16,
        "vertical_rate": 0.33,
        "sensors": null,
        "geo_altitude": -22.86,
        "squawk": null,
        "spi": false,
        "position_source": 0,
        "category": 0
    },
    {
        "icao24": "a69bcd",
        "callsign": "DAL685  ",
        "origin_country": "United States",
        "time_position": 1750657687,
        "last_contact": 1750657687,
        "longitude": -116.6783,
        "latitude": 32.7183,
        "baro_altitude": 2400.3,
        "on_ground": false,
        "velocity": 136.52,
        "true_track": 264.16,
        "vertical_rate": -4.55,
        "sensors": null,
        "geo_altitude": 2461.26,
        "squawk": "3007",
        "spi": false,
        "position_source": 0,
        "category": 0
    },
    {
        "icao24": "a1ea70",
        "callsign": "SWA3631 ",
        "origin_country": "United States",
        "time_position": 1750657686,
        "last_contact": 1750657686,
        "longitude": -116.0936,
        "latitude": 32.7667,
        "baro_altitude": 4930.14,
        "on_ground": false,
        "velocity": 191.1,
        "true_track": 264.9,
        "vertical_rate": -12.03,
        "sensors": null,
        "geo_altitude": 5158.74,
        "squawk": "2564",
        "spi": false,
        "position_source": 0,
        "category": 0
    },
    {
        "icao24": "a25e79",
        "callsign": "CXK204  ",
        "origin_country": "United States",
        "time_position": 1750657687,
        "last_contact": 1750657687,
        "longitude": -117.2664,
        "latitude": 33.1443,
        "baro_altitude": 411.48,
        "on_ground": false,
        "velocity": 33.6,
        "true_track": 115.39,
        "vertical_rate": -2.93,
        "sensors": null,
        "geo_altitude": 381,
        "squawk": null,
        "spi": false,
        "position_source": 0,
        "category": 0
    },
    {
        "icao24": "ac2a8e",
        "callsign": "N883SD  ",
        "origin_country": "United States",
        "time_position": 1750657687,
        "last_contact": 1750657687,
        "longitude": -117.1129,
        "latitude": 32.7782,
        "baro_altitude": 762,
        "on_ground": false,
        "velocity": 42.33,
        "true_track": 110.64,
        "vertical_rate": 0.33,
        "sensors": null,
        "geo_altitude": 731.52,
        "squawk": null,
        "spi": false,
        "position_source": 0,
        "category": 0
    },
    {
        "icao24": "a35e61",
        "callsign": "ASI7059 ",
        "origin_country": "United States",
        "time_position": 1750657686,
        "last_contact": 1750657686,
        "longitude": -116.8524,
        "latitude": 33.0283,
        "baro_altitude": 2743.2,
        "on_ground": false,
        "velocity": 74.54,
        "true_track": 62.9,
        "vertical_rate": -0.65,
        "sensors": null,
        "geo_altitude": 2804.16,
        "squawk": null,
        "spi": false,
        "position_source": 0,
        "category": 0
    },
    {
        "icao24": "0c218b",
        "callsign": "CMP302  ",
        "origin_country": "Panama",
        "time_position": 1750657686,
        "last_contact": 1750657686,
        "longitude": -117.1356,
        "latitude": 33.203,
        "baro_altitude": 5242.56,
        "on_ground": false,
        "velocity": 180.57,
        "true_track": 279.68,
        "vertical_rate": -10.4,
        "sensors": null,
        "geo_altitude": 5471.16,
        "squawk": "0161",
        "spi": false,
        "position_source": 0,
        "category": 0
    },
    {
        "icao24": "0c2166",
        "callsign": "CMP362  ",
        "origin_country": "Panama",
        "time_position": 1750657687,
        "last_contact": 1750657687,
        "longitude": -116.3838,
        "latitude": 32.7649,
        "baro_altitude": 8953.5,
        "on_ground": false,
        "velocity": 245.98,
        "true_track": 117.53,
        "vertical_rate": 3.25,
        "sensors": null,
        "geo_altitude": 9380.22,
        "squawk": "7742",
        "spi": false,
        "position_source": 0,
        "category": 0
    }
]